keras_experiment_recorder/__init__.py
keras_experiment_recorder/_callbacks.py
Keras_Experiment_Recorder-0.1.1.dist-info/LICENSE
Keras_Experiment_Recorder-0.1.1.dist-info/METADATA
Keras_Experiment_Recorder-0.1.1.dist-info/WHEEL
Keras_Experiment_Recorder-0.1.1.dist-info/top_level.txt
Keras_Experiment_Recorder-0.1.1.dist-info/RECORD
