Metadata-Version: 2.1
Name: Keras-Experiment-Recorder
Version: 0.1.1
Summary: A keras extension (callback) to record details of a training task
Home-page: https://github.com/ksachdeva/keras-experiment-recorder.git
Author: Kapil Sachdeva
Author-email: notanemail@gmail.com
License: Apache-2.0
Platform: UNKNOWN
Classifier: Development Status :: 3 - Alpha
Classifier: Intended Audience :: Developers
Classifier: Intended Audience :: Education
Classifier: Intended Audience :: Science/Research
Classifier: License :: OSI Approved :: MIT License
Classifier: Programming Language :: Python :: 2
Classifier: Programming Language :: Python :: 2.7
Classifier: Programming Language :: Python :: 3
Classifier: Programming Language :: Python :: 3.6
Classifier: Topic :: Software Development :: Libraries
Classifier: Topic :: Software Development :: Libraries :: Python Modules
